strawberrypie/__init__.py
Strawberrypie-0.0.1.dist-info/METADATA
Strawberrypie-0.0.1.dist-info/WHEEL
Strawberrypie-0.0.1.dist-info/top_level.txt
Strawberrypie-0.0.1.dist-info/RECORD
