Metadata-Version: 2.1
Name: Strawberrypie
Version: 0.0.1
Summary: UNKNOWN
Home-page: UNKNOWN
Author: astroxiii (abderrahim mokhnache)
Author-email: <abderrahimokhnache@gmail.com>
License: UNKNOWN
Keywords: python
Platform: UNKNOWN
Classifier: Development Status :: 3 - Alpha
Classifier: Intended Audience :: Developers
Classifier: Programming Language :: Python :: 3
Classifier: Operating System :: Unix
Classifier: Operating System :: MacOS :: MacOS X
Classifier: Operating System :: Microsoft :: Windows
